<?xml version="1.0" encoding="UTF-8"?>
<objects serializationModel="Studio.02.02.00">
	<object class="AudioFile" id="{96b07694-9bc2-4052-ac87-a3a9096a41e0}">
		<property name="assetPath">
			<value>1.2. R.wav</value>
		</property>
		<property name="frequencyInKHz">
			<value>44.0999985</value>
		</property>
		<property name="channelCount">
			<value>2</value>
		</property>
		<property name="length">
			<value>2.5</value>
		</property>
		<relationship name="masterAssetFolder">
			<destination>{fc8d97d3-c835-43db-9efd-5b8f0d6b7e72}</destination>
		</relationship>
	</object>
</objects>
